cielo24cli.py
setup.py
cielo24cli.egg-info/PKG-INFO
cielo24cli.egg-info/SOURCES.txt
cielo24cli.egg-info/dependency_links.txt
cielo24cli.egg-info/requires.txt
cielo24cli.egg-info/top_level.txt