Metadata-Version: 1.0
Name: cielo24cli
Version: 1.0.9
Summary: Commmand line for cielo24 package.
Home-page: http://www.cielo24.com
Author: cielo24
Author-email: support@cielo24.com
License: UNKNOWN
Platform: UNKNOWN
